{
    "description": "",
    "tags": [
        {
            "id": 590156,
            "tagId": 4899,
            "name": "Cabernet Franc",
            "value": null,
            "labelerLogin": "gr@datasetninja.com",
            "createdAt": "2023-08-05T15:33:28.467Z",
            "updatedAt": "2023-08-05T15:33:28.467Z"
        }
    ],
    "size": {
        "height": 1365,
        "width": 2048
    },
    "objects": [
        {
            "id": 15729986,
            "classId": 28267,
            "description": "",
            "geometryType": "rectangle",
            "labelerLogin": "gr@datasetninja.com",
            "createdAt": "2023-08-05T15:33:28.474Z",
            "updatedAt": "2023-08-05T15:33:28.474Z",
            "tags": [],
            "classTitle": "uva_bbox",
            "points": {
                "exterior": [
                    [
                        13,
                        744
                    ],
                    [
                        133,
                        1008
                    ]
                ],
                "interior": []
            }
        },
        {
            "id": 15729985,
            "classId": 28267,
            "description": "",
            "geometryType": "rectangle",
            "labelerLogin": "gr@datasetninja.com",
            "createdAt": "2023-08-05T15:33:28.474Z",
            "updatedAt": "2023-08-05T15:33:28.474Z",
            "tags": [],
            "classTitle": "uva_bbox",
            "points": {
                "exterior": [
                    [
                        10,
                        622
                    ],
                    [
                        123,
                        740
                    ]
                ],
                "interior": []
            }
        },
        {
            "id": 15729984,
            "classId": 28267,
            "description": "",
            "geometryType": "rectangle",
            "labelerLogin": "gr@datasetninja.com",
            "createdAt": "2023-08-05T15:33:28.474Z",
            "updatedAt": "2023-08-05T15:33:28.474Z",
            "tags": [],
            "classTitle": "uva_bbox",
            "points": {
                "exterior": [
                    [
                        182,
                        632
                    ],
                    [
                        336,
                        874
                    ]
                ],
                "interior": []
            }
        },
        {
            "id": 15729983,
            "classId": 28267,
            "description": "",
            "geometryType": "rectangle",
            "labelerLogin": "gr@datasetninja.com",
            "createdAt": "2023-08-05T15:33:28.473Z",
            "updatedAt": "2023-08-05T15:33:28.473Z",
            "tags": [],
            "classTitle": "uva_bbox",
            "points": {
                "exterior": [
                    [
                        82,
                        1178
                    ],
                    [
                        223,
                        1360
                    ]
                ],
                "interior": []
            }
        },
        {
            "id": 15729982,
            "classId": 28267,
            "description": "",
            "geometryType": "rectangle",
            "labelerLogin": "gr@datasetninja.com",
            "createdAt": "2023-08-05T15:33:28.473Z",
            "updatedAt": "2023-08-05T15:33:28.473Z",
            "tags": [],
            "classTitle": "uva_bbox",
            "points": {
                "exterior": [
                    [
                        591,
                        771
                    ],
                    [
                        684,
                        970
                    ]
                ],
                "interior": []
            }
        },
        {
            "id": 15729981,
            "classId": 28267,
            "description": "",
            "geometryType": "rectangle",
            "labelerLogin": "gr@datasetninja.com",
            "createdAt": "2023-08-05T15:33:28.473Z",
            "updatedAt": "2023-08-05T15:33:28.473Z",
            "tags": [],
            "classTitle": "uva_bbox",
            "points": {
                "exterior": [
                    [
                        391,
                        667
                    ],
                    [
                        591,
                        856
                    ]
                ],
                "interior": []
            }
        },
        {
            "id": 15729980,
            "classId": 28267,
            "description": "",
            "geometryType": "rectangle",
            "labelerLogin": "gr@datasetninja.com",
            "createdAt": "2023-08-05T15:33:28.473Z",
            "updatedAt": "2023-08-05T15:33:28.473Z",
            "tags": [],
            "classTitle": "uva_bbox",
            "points": {
                "exterior": [
                    [
                        440,
                        825
                    ],
                    [
                        592,
                        943
                    ]
                ],
                "interior": []
            }
        },
        {
            "id": 15729979,
            "classId": 28267,
            "description": "",
            "geometryType": "rectangle",
            "labelerLogin": "gr@datasetninja.com",
            "createdAt": "2023-08-05T15:33:28.473Z",
            "updatedAt": "2023-08-05T15:33:28.473Z",
            "tags": [],
            "classTitle": "uva_bbox",
            "points": {
                "exterior": [
                    [
                        671,
                        844
                    ],
                    [
                        829,
                        1153
                    ]
                ],
                "interior": []
            }
        },
        {
            "id": 15729978,
            "classId": 28267,
            "description": "",
            "geometryType": "rectangle",
            "labelerLogin": "gr@datasetninja.com",
            "createdAt": "2023-08-05T15:33:28.472Z",
            "updatedAt": "2023-08-05T15:33:28.472Z",
            "tags": [],
            "classTitle": "uva_bbox",
            "points": {
                "exterior": [
                    [
                        974,
                        709
                    ],
                    [
                        1129,
                        981
                    ]
                ],
                "interior": []
            }
        },
        {
            "id": 15729977,
            "classId": 28267,
            "description": "",
            "geometryType": "rectangle",
            "labelerLogin": "gr@datasetninja.com",
            "createdAt": "2023-08-05T15:33:28.472Z",
            "updatedAt": "2023-08-05T15:33:28.472Z",
            "tags": [],
            "classTitle": "uva_bbox",
            "points": {
                "exterior": [
                    [
                        787,
                        638
                    ],
                    [
                        966,
                        984
                    ]
                ],
                "interior": []
            }
        },
        {
            "id": 15729976,
            "classId": 28267,
            "description": "",
            "geometryType": "rectangle",
            "labelerLogin": "gr@datasetninja.com",
            "createdAt": "2023-08-05T15:33:28.472Z",
            "updatedAt": "2023-08-05T15:33:28.472Z",
            "tags": [],
            "classTitle": "uva_bbox",
            "points": {
                "exterior": [
                    [
                        873,
                        889
                    ],
                    [
                        954,
                        1050
                    ]
                ],
                "interior": []
            }
        },
        {
            "id": 15729975,
            "classId": 28267,
            "description": "",
            "geometryType": "rectangle",
            "labelerLogin": "gr@datasetninja.com",
            "createdAt": "2023-08-05T15:33:28.471Z",
            "updatedAt": "2023-08-05T15:33:28.471Z",
            "tags": [],
            "classTitle": "uva_bbox",
            "points": {
                "exterior": [
                    [
                        1226,
                        864
                    ],
                    [
                        1371,
                        1133
                    ]
                ],
                "interior": []
            }
        },
        {
            "id": 15729974,
            "classId": 28267,
            "description": "",
            "geometryType": "rectangle",
            "labelerLogin": "gr@datasetninja.com",
            "createdAt": "2023-08-05T15:33:28.471Z",
            "updatedAt": "2023-08-05T15:33:28.471Z",
            "tags": [],
            "classTitle": "uva_bbox",
            "points": {
                "exterior": [
                    [
                        1111,
                        412
                    ],
                    [
                        1378,
                        870
                    ]
                ],
                "interior": []
            }
        },
        {
            "id": 15729973,
            "classId": 28267,
            "description": "",
            "geometryType": "rectangle",
            "labelerLogin": "gr@datasetninja.com",
            "createdAt": "2023-08-05T15:33:28.470Z",
            "updatedAt": "2023-08-05T15:33:28.470Z",
            "tags": [],
            "classTitle": "uva_bbox",
            "points": {
                "exterior": [
                    [
                        1412,
                        952
                    ],
                    [
                        1526,
                        1057
                    ]
                ],
                "interior": []
            }
        },
        {
            "id": 15729972,
            "classId": 28267,
            "description": "",
            "geometryType": "rectangle",
            "labelerLogin": "gr@datasetninja.com",
            "createdAt": "2023-08-05T15:33:28.470Z",
            "updatedAt": "2023-08-05T15:33:28.470Z",
            "tags": [],
            "classTitle": "uva_bbox",
            "points": {
                "exterior": [
                    [
                        1526,
                        971
                    ],
                    [
                        1620,
                        1118
                    ]
                ],
                "interior": []
            }
        },
        {
            "id": 15729971,
            "classId": 28267,
            "description": "",
            "geometryType": "rectangle",
            "labelerLogin": "gr@datasetninja.com",
            "createdAt": "2023-08-05T15:33:28.470Z",
            "updatedAt": "2023-08-05T15:33:28.470Z",
            "tags": [],
            "classTitle": "uva_bbox",
            "points": {
                "exterior": [
                    [
                        1453,
                        802
                    ],
                    [
                        1575,
                        919
                    ]
                ],
                "interior": []
            }
        },
        {
            "id": 15729970,
            "classId": 28267,
            "description": "",
            "geometryType": "rectangle",
            "labelerLogin": "gr@datasetninja.com",
            "createdAt": "2023-08-05T15:33:28.470Z",
            "updatedAt": "2023-08-05T15:33:28.470Z",
            "tags": [],
            "classTitle": "uva_bbox",
            "points": {
                "exterior": [
                    [
                        1532,
                        682
                    ],
                    [
                        1667,
                        959
                    ]
                ],
                "interior": []
            }
        },
        {
            "id": 15729969,
            "classId": 28267,
            "description": "",
            "geometryType": "rectangle",
            "labelerLogin": "gr@datasetninja.com",
            "createdAt": "2023-08-05T15:33:28.469Z",
            "updatedAt": "2023-08-05T15:33:28.469Z",
            "tags": [],
            "classTitle": "uva_bbox",
            "points": {
                "exterior": [
                    [
                        1594,
                        590
                    ],
                    [
                        1764,
                        846
                    ]
                ],
                "interior": []
            }
        },
        {
            "id": 15729968,
            "classId": 28267,
            "description": "",
            "geometryType": "rectangle",
            "labelerLogin": "gr@datasetninja.com",
            "createdAt": "2023-08-05T15:33:28.469Z",
            "updatedAt": "2023-08-05T15:33:28.469Z",
            "tags": [],
            "classTitle": "uva_bbox",
            "points": {
                "exterior": [
                    [
                        1666,
                        756
                    ],
                    [
                        1775,
                        916
                    ]
                ],
                "interior": []
            }
        },
        {
            "id": 15729967,
            "classId": 28267,
            "description": "",
            "geometryType": "rectangle",
            "labelerLogin": "gr@datasetninja.com",
            "createdAt": "2023-08-05T15:33:28.468Z",
            "updatedAt": "2023-08-05T15:33:28.468Z",
            "tags": [],
            "classTitle": "uva_bbox",
            "points": {
                "exterior": [
                    [
                        1780,
                        781
                    ],
                    [
                        1912,
                        1127
                    ]
                ],
                "interior": []
            }
        },
        {
            "id": 15729966,
            "classId": 28267,
            "description": "",
            "geometryType": "rectangle",
            "labelerLogin": "gr@datasetninja.com",
            "createdAt": "2023-08-05T15:33:28.468Z",
            "updatedAt": "2023-08-05T15:33:28.468Z",
            "tags": [],
            "classTitle": "uva_bbox",
            "points": {
                "exterior": [
                    [
                        1861,
                        688
                    ],
                    [
                        2046,
                        846
                    ]
                ],
                "interior": []
            }
        },
        {
            "id": 15729965,
            "classId": 28267,
            "description": "",
            "geometryType": "rectangle",
            "labelerLogin": "gr@datasetninja.com",
            "createdAt": "2023-08-05T15:33:28.468Z",
            "updatedAt": "2023-08-05T15:33:28.468Z",
            "tags": [],
            "classTitle": "uva_bbox",
            "points": {
                "exterior": [
                    [
                        1924,
                        824
                    ],
                    [
                        2047,
                        1004
                    ]
                ],
                "interior": []
            }
        }
    ]
}